LICENSE
README.md
setup.cfg
setup.py
undefined/__init__.py
undefined_oc.egg-info/PKG-INFO
undefined_oc.egg-info/SOURCES.txt
undefined_oc.egg-info/dependency_links.txt
undefined_oc.egg-info/top_level.txt
undefined_oc.egg-info/zip-safe