Metadata-Version: 2.1
Name: undefined-oc
Version: 1.0.0
Summary: undefined: simulates the JavaScript undefined behaviour in Python
Home-page: https://github.com/ouroboroscoding/undefined-python
Author: Chris Nasr - Ouroboros Coding Inc.
Author-email: chris@ouroboroscoding.com
License: MIT
Project-URL: Source, https://github.com/ouroboroscoding/undefined-python
Project-URL: Tracker, https://github.com/ouroboroscoding/undefined-python/issues
Keywords: javascript,undefined
Platform: UNKNOWN
Requires-Python: >=3.10
License-File: LICENSE
